[
  {
    "model": "groups.group",
    "pk": "259b79ef-2d5b-4ca6-a65d-b8539c24e947",
    "fields": {
      "created_at": "2023-08-21T13:23:19.361Z",
      "updated_at": "2023-08-21T13:23:19.361Z",
      "name": "Graffiti",
      "slug": "graffiti",
      "public_name": "Graffiti",
      "is_public_accessible": false,
      "is_active": true,
      "meta": {
        "msb": {
          "code": "3",
          "onderwerpen": [
            {
              "code": "9",
              "magMelden": true,
              "omschrijving": "graffiti-discriminerend",
              "magDoorverwijzen": true,
              "indicatieBestandsbeheer": false
            },
            {
              "code": "10",
              "magMelden": true,
              "omschrijving": "graffiti-overig",
              "magDoorverwijzen": true,
              "indicatieBestandsbeheer": false
            }
          ],
          "omschrijving": "Graffiti"
        }
      }
    }
  },
  {
    "model": "groups.group",
    "pk": "27043605-1cc2-4315-bbf3-070f1a9ed212",
    "fields": {
      "created_at": "2023-08-21T13:23:19.365Z",
      "updated_at": "2023-08-21T13:23:19.365Z",
      "name": "Singels en sloten",
      "slug": "singels-en-sloten",
      "public_name": "Singels en sloten",
      "is_public_accessible": false,
      "is_active": true,
      "meta": {
        "msb": {
          "code": "8",
          "onderwerpen": [
            {
              "code": "33",
              "magMelden": true,
              "omschrijving": "beschoeiingen",
              "magDoorverwijzen": true,
              "indicatieBestandsbeheer": false
            },
            {
              "code": "115",
              "magMelden": true,
              "omschrijving": "drijfvuil in singel",
              "magDoorverwijzen": true,
              "indicatieBestandsbeheer": false
            },
            {
              "code": "297",
              "magMelden": true,
              "omschrijving": "Fonteinen",
              "magDoorverwijzen": true,
              "indicatieBestandsbeheer": false
            },
            {
              "code": "35",
              "magMelden": true,
              "omschrijving": "singel ",
              "magDoorverwijzen": true,
              "indicatieBestandsbeheer": false
            },
            {
              "code": "34",
              "magMelden": true,
              "omschrijving": "zinkvuil/vloeistoffen in singel",
              "magDoorverwijzen": true,
              "indicatieBestandsbeheer": false
            }
          ],
          "omschrijving": "Singels en sloten"
        }
      }
    }
  },
  {
    "model": "groups.group",
    "pk": "30df10e5-d2f0-41da-809c-5c4d3d9e8c51",
    "fields": {
      "created_at": "2023-08-21T13:23:19.371Z",
      "updated_at": "2023-08-21T13:23:19.371Z",
      "name": "Wateroverlast / riolering",
      "slug": "wateroverlast-riolering",
      "public_name": "Wateroverlast / riolering",
      "is_public_accessible": false,
      "is_active": true,
      "meta": {
        "msb": {
          "code": "12",
          "onderwerpen": [
            {
              "code": "51",
              "magMelden": true,
              "omschrijving": "hoofdriool",
              "magDoorverwijzen": true,
              "indicatieBestandsbeheer": false
            },
            {
              "code": "218",
              "magMelden": false,
              "omschrijving": "Rioolaansluiting (verstopping)",
              "magDoorverwijzen": true,
              "indicatieBestandsbeheer": false
            },
            {
              "code": "98",
              "magMelden": true,
              "omschrijving": "stankoverlast",
              "magDoorverwijzen": true,
              "indicatieBestandsbeheer": false
            },
            {
              "code": "114",
              "magMelden": true,
              "omschrijving": "storing gemaal",
              "magDoorverwijzen": true,
              "indicatieBestandsbeheer": false
            },
            {
              "code": "55",
              "magMelden": true,
              "omschrijving": "straatkolk (verstopt)",
              "magDoorverwijzen": true,
              "indicatieBestandsbeheer": false
            },
            {
              "code": "219",
              "magMelden": false,
              "omschrijving": "Water in de kruipruimte, de kelder of in een tuin",
              "magDoorverwijzen": true,
              "indicatieBestandsbeheer": false
            },
            {
              "code": "300",
              "magMelden": true,
              "omschrijving": "Water- of rioolpersleiding",
              "magDoorverwijzen": true,
              "indicatieBestandsbeheer": false
            }
          ],
          "omschrijving": "Wateroverlast / riolering"
        }
      }
    }
  },
  {
    "model": "groups.group",
    "pk": "341b616c-ae10-4234-87c2-52dac4493387",
    "fields": {
      "created_at": "2023-08-21T13:23:19.364Z",
      "updated_at": "2023-08-21T13:23:19.364Z",
      "name": "Parkeeroverlast",
      "slug": "parkeeroverlast",
      "public_name": "Parkeeroverlast",
      "is_public_accessible": false,
      "is_active": true,
      "meta": {
        "msb": {
          "code": "35",
          "onderwerpen": [
            {
              "code": "123",
              "magMelden": true,
              "omschrijving": "aanhangers/caravans",
              "magDoorverwijzen": true,
              "indicatieBestandsbeheer": false
            },
            {
              "code": "289",
              "magMelden": true,
              "omschrijving": "Hinderlijk geparkeerde (brom-)fiets",
              "magDoorverwijzen": true,
              "indicatieBestandsbeheer": false
            },
            {
              "code": "216",
              "magMelden": true,
              "omschrijving": "Parkeeroverlast",
              "magDoorverwijzen": true,
              "indicatieBestandsbeheer": false
            },
            {
              "code": "290",
              "magMelden": true,
              "omschrijving": "Te lang geparkeerde (brom-)fiets",
              "magDoorverwijzen": true,
              "indicatieBestandsbeheer": false
            }
          ],
          "omschrijving": "Parkeeroverlast"
        }
      }
    }
  },
  {
    "model": "groups.group",
    "pk": "3925aebe-e96c-42c1-b27b-bbb3369fb7f4",
    "fields": {
      "created_at": "2023-08-21T13:23:19.363Z",
      "updated_at": "2023-08-21T13:23:19.363Z",
      "name": "Overige onderwerpen",
      "slug": "overige-onderwerpen",
      "public_name": "Overige onderwerpen",
      "is_public_accessible": false,
      "is_active": true,
      "meta": {
        "msb": {
          "code": "6",
          "onderwerpen": [
            {
              "code": "287",
              "magMelden": true,
              "omschrijving": "Marktvoorzieningen",
              "magDoorverwijzen": true,
              "indicatieBestandsbeheer": false
            },
            {
              "code": "23",
              "magMelden": true,
              "omschrijving": "Openbare werken algemeen",
              "magDoorverwijzen": true,
              "indicatieBestandsbeheer": false
            },
            {
              "code": "140",
              "magMelden": true,
              "omschrijving": "Schone Stad algemeen",
              "magDoorverwijzen": true,
              "indicatieBestandsbeheer": false
            },
            {
              "code": "302",
              "magMelden": true,
              "omschrijving": "Stadsontwikkeling Algemeen",
              "magDoorverwijzen": true,
              "indicatieBestandsbeheer": false
            },
            {
              "code": "152",
              "magMelden": true,
              "omschrijving": "Toezicht & Handhaving algemeen",
              "magDoorverwijzen": true,
              "indicatieBestandsbeheer": false
            }
          ],
          "omschrijving": "Overige onderwerpen"
        }
      }
    }
  },
  {
    "model": "groups.group",
    "pk": "43d598d9-3446-46ae-be62-ef6480cb4d67",
    "fields": {
      "created_at": "2023-08-21T13:23:19.369Z",
      "updated_at": "2023-08-21T13:23:19.369Z",
      "name": "Straatverlichting",
      "slug": "straatverlichting",
      "public_name": "Straatverlichting",
      "is_public_accessible": false,
      "is_active": true,
      "meta": {
        "msb": {
          "code": "5",
          "onderwerpen": [
            {
              "code": "165",
              "magMelden": true,
              "omschrijving": "beschadigde lichtmast",
              "magDoorverwijzen": true,
              "indicatieBestandsbeheer": false
            },
            {
              "code": "173",
              "magMelden": true,
              "omschrijving": "brandt geen verlichting in gehele straat",
              "magDoorverwijzen": true,
              "indicatieBestandsbeheer": false
            },
            {
              "code": "164",
              "magMelden": true,
              "omschrijving": "lamp(en) uit",
              "magDoorverwijzen": true,
              "indicatieBestandsbeheer": false
            },
            {
              "code": "167",
              "magMelden": true,
              "omschrijving": "lichtmastluikje staat open / bedrading zichtbaar",
              "magDoorverwijzen": true,
              "indicatieBestandsbeheer": false
            },
            {
              "code": "166",
              "magMelden": true,
              "omschrijving": "scheefstaande lichtmast",
              "magDoorverwijzen": true,
              "indicatieBestandsbeheer": false
            },
            {
              "code": "172",
              "magMelden": true,
              "omschrijving": "verlichting brandt ook overdag                ",
              "magDoorverwijzen": true,
              "indicatieBestandsbeheer": false
            },
            {
              "code": "168",
              "magMelden": true,
              "omschrijving": "verlichting overig: (geef omschrijving)",
              "magDoorverwijzen": true,
              "indicatieBestandsbeheer": false
            }
          ],
          "omschrijving": "Straatverlichting"
        }
      }
    }
  },
  {
    "model": "groups.group",
    "pk": "48f211d6-8d12-4868-97dd-64b2bca9f552",
    "fields": {
      "created_at": "2023-08-21T13:23:19.372Z",
      "updated_at": "2023-08-21T13:23:19.372Z",
      "name": "Weg (fiets/voet)pad brug",
      "slug": "weg-fietsvoetpad-brug",
      "public_name": "Weg (fiets/voet)pad brug",
      "is_public_accessible": false,
      "is_active": true,
      "meta": {
        "msb": {
          "code": "13",
          "onderwerpen": [
            {
              "code": "14",
              "magMelden": true,
              "omschrijving": "boomwortels",
              "magDoorverwijzen": true,
              "indicatieBestandsbeheer": false
            },
            {
              "code": "129",
              "magMelden": true,
              "omschrijving": "brug",
              "magDoorverwijzen": true,
              "indicatieBestandsbeheer": false
            },
            {
              "code": "8",
              "magMelden": true,
              "omschrijving": "fietspad",
              "magDoorverwijzen": true,
              "indicatieBestandsbeheer": false
            },
            {
              "code": "183",
              "magMelden": true,
              "omschrijving": "gebiedsgericht",
              "magDoorverwijzen": false,
              "indicatieBestandsbeheer": false
            },
            {
              "code": "89",
              "magMelden": true,
              "omschrijving": "gladheid (sneeuw-ijzel-vorst)",
              "magDoorverwijzen": true,
              "indicatieBestandsbeheer": false
            },
            {
              "code": "85",
              "magMelden": true,
              "omschrijving": "invalide-oprit",
              "magDoorverwijzen": true,
              "indicatieBestandsbeheer": false
            },
            {
              "code": "195",
              "magMelden": true,
              "omschrijving": "POK Asfalt: Gieten",
              "magDoorverwijzen": false,
              "indicatieBestandsbeheer": false
            },
            {
              "code": "194",
              "magMelden": true,
              "omschrijving": "POK Asfalt: Rood",
              "magDoorverwijzen": false,
              "indicatieBestandsbeheer": false
            },
            {
              "code": "196",
              "magMelden": true,
              "omschrijving": "POK Asfalt: SIR",
              "magDoorverwijzen": false,
              "indicatieBestandsbeheer": false
            },
            {
              "code": "193",
              "magMelden": true,
              "omschrijving": "POK Asfalt: Zwart",
              "magDoorverwijzen": false,
              "indicatieBestandsbeheer": false
            },
            {
              "code": "73",
              "magMelden": true,
              "omschrijving": "rijweg",
              "magDoorverwijzen": true,
              "indicatieBestandsbeheer": false
            },
            {
              "code": "131",
              "magMelden": true,
              "omschrijving": "sluis",
              "magDoorverwijzen": true,
              "indicatieBestandsbeheer": false
            },
            {
              "code": "132",
              "magMelden": true,
              "omschrijving": "tunnels/viaducten",
              "magDoorverwijzen": true,
              "indicatieBestandsbeheer": false
            },
            {
              "code": "78",
              "magMelden": true,
              "omschrijving": "verkeersdrempel",
              "magDoorverwijzen": true,
              "indicatieBestandsbeheer": false
            },
            {
              "code": "75",
              "magMelden": true,
              "omschrijving": "voetpad",
              "magDoorverwijzen": true,
              "indicatieBestandsbeheer": false
            }
          ],
          "omschrijving": "Weg (fiets/voet)pad brug"
        }
      }
    }
  },
  {
    "model": "groups.group",
    "pk": "4c6a8038-1c14-482f-abf9-340875a86573",
    "fields": {
      "created_at": "2023-08-21T13:23:19.359Z",
      "updated_at": "2023-08-21T13:23:19.359Z",
      "name": "Bomen, planten, gras",
      "slug": "bomen-planten-gras",
      "public_name": "Bomen, planten, gras",
      "is_public_accessible": false,
      "is_active": true,
      "meta": {
        "msb": {
          "code": "24",
          "onderwerpen": [
            {
              "code": "11",
              "magMelden": true,
              "omschrijving": "bloembakken",
              "magDoorverwijzen": true,
              "indicatieBestandsbeheer": false
            },
            {
              "code": "12",
              "magMelden": true,
              "omschrijving": "Bomen",
              "magDoorverwijzen": true,
              "indicatieBestandsbeheer": false
            },
            {
              "code": "151",
              "magMelden": true,
              "omschrijving": "Gras",
              "magDoorverwijzen": true,
              "indicatieBestandsbeheer": false
            },
            {
              "code": "294",
              "magMelden": true,
              "omschrijving": "Japanse Duizendknoop",
              "magDoorverwijzen": true,
              "indicatieBestandsbeheer": false
            },
            {
              "code": "20",
              "magMelden": true,
              "omschrijving": "plantsoenen",
              "magDoorverwijzen": true,
              "indicatieBestandsbeheer": false
            }
          ],
          "omschrijving": "Bomen, planten, gras"
        }
      }
    }
  },
  {
    "model": "groups.group",
    "pk": "53fff76c-6a62-4928-bbb8-ca2653dd0067",
    "fields": {
      "created_at": "2023-08-21T13:23:19.360Z",
      "updated_at": "2023-08-21T13:23:19.360Z",
      "name": "Gevaarlijk (straat)afval",
      "slug": "gevaarlijk-straatafval",
      "public_name": "Gevaarlijk (straat)afval",
      "is_public_accessible": false,
      "is_active": true,
      "meta": {
        "msb": {
          "code": "20",
          "onderwerpen": [
            {
              "code": "119",
              "magMelden": true,
              "omschrijving": "accu",
              "magDoorverwijzen": true,
              "indicatieBestandsbeheer": false
            },
            {
              "code": "91",
              "magMelden": true,
              "omschrijving": "asbest",
              "magDoorverwijzen": true,
              "indicatieBestandsbeheer": false
            },
            {
              "code": "120",
              "magMelden": true,
              "omschrijving": "gastank/brandblusapparatuur",
              "magDoorverwijzen": true,
              "indicatieBestandsbeheer": false
            },
            {
              "code": "79",
              "magMelden": true,
              "omschrijving": "injectienaalden/spuiten",
              "magDoorverwijzen": true,
              "indicatieBestandsbeheer": false
            },
            {
              "code": "92",
              "magMelden": true,
              "omschrijving": "(klein) chemisch afval",
              "magDoorverwijzen": true,
              "indicatieBestandsbeheer": false
            },
            {
              "code": "305",
              "magMelden": true,
              "omschrijving": "Lachgasfles(sen)",
              "magDoorverwijzen": true,
              "indicatieBestandsbeheer": false
            },
            {
              "code": "88",
              "magMelden": true,
              "omschrijving": "(olie)lekkage/morsing",
              "magDoorverwijzen": true,
              "indicatieBestandsbeheer": false
            },
            {
              "code": "118",
              "magMelden": true,
              "omschrijving": "(olie)vaten",
              "magDoorverwijzen": true,
              "indicatieBestandsbeheer": false
            },
            {
              "code": "122",
              "magMelden": true,
              "omschrijving": "onbekende stoffen",
              "magDoorverwijzen": true,
              "indicatieBestandsbeheer": false
            },
            {
              "code": "121",
              "magMelden": true,
              "omschrijving": "uitgebrande voertuigen (herstel wegdek)",
              "magDoorverwijzen": true,
              "indicatieBestandsbeheer": false
            }
          ],
          "omschrijving": "Gevaarlijk (straat)afval"
        }
      }
    }
  },
  {
    "model": "groups.group",
    "pk": "5722e9c5-99e6-45d3-8335-69c623b3710f",
    "fields": {
      "created_at": "2023-08-21T13:23:19.375Z",
      "updated_at": "2023-08-21T13:23:19.375Z",
      "name": "Wrakken",
      "slug": "wrakken",
      "public_name": "Wrakken",
      "is_public_accessible": false,
      "is_active": true,
      "meta": {
        "msb": {
          "code": "26",
          "onderwerpen": [
            {
              "code": "90",
              "magMelden": true,
              "omschrijving": "(Brom-)fietswrak",
              "magDoorverwijzen": true,
              "indicatieBestandsbeheer": false
            },
            {
              "code": "117",
              "magMelden": true,
              "omschrijving": "wrak - auto",
              "magDoorverwijzen": true,
              "indicatieBestandsbeheer": false
            }
          ],
          "omschrijving": "Wrakken"
        }
      }
    }
  },
  {
    "model": "groups.group",
    "pk": "67c1c7a7-d4c3-4c4f-a745-0e23c9f23ba2",
    "fields": {
      "created_at": "2023-08-21T13:23:19.362Z",
      "updated_at": "2023-08-21T13:23:19.362Z",
      "name": "Meldkamer Stadsbeheer",
      "slug": "meldkamer-stadsbeheer",
      "public_name": "Meldkamer Stadsbeheer",
      "is_public_accessible": false,
      "is_active": true,
      "meta": {
        "msb": {
          "code": "49",
          "onderwerpen": [
            {
              "code": "266",
              "magMelden": true,
              "omschrijving": "Flying Squads Schone Stad",
              "magDoorverwijzen": false,
              "indicatieBestandsbeheer": false
            },
            {
              "code": "265",
              "magMelden": true,
              "omschrijving": "Flying Squads T&H",
              "magDoorverwijzen": false,
              "indicatieBestandsbeheer": false
            }
          ],
          "omschrijving": "Meldkamer Stadsbeheer"
        }
      }
    }
  },
  {
    "model": "groups.group",
    "pk": "6dd09e68-dc0c-408a-b0b0-92d7ce4e2814",
    "fields": {
      "created_at": "2023-08-21T13:23:19.363Z",
      "updated_at": "2023-08-21T13:23:19.363Z",
      "name": "Overlast",
      "slug": "overlast",
      "public_name": "Overlast",
      "is_public_accessible": false,
      "is_active": true,
      "meta": {
        "msb": {
          "code": "48",
          "onderwerpen": [
            {
              "code": "288",
              "magMelden": true,
              "omschrijving": "Overlast markten",
              "magDoorverwijzen": true,
              "indicatieBestandsbeheer": false
            }
          ],
          "omschrijving": "Overlast"
        }
      }
    }
  },
  {
    "model": "groups.group",
    "pk": "7699ad53-7232-45e6-81f2-594af2c07da0",
    "fields": {
      "created_at": "2023-08-21T13:23:19.360Z",
      "updated_at": "2023-08-21T13:23:19.360Z",
      "name": "Dieren",
      "slug": "dieren",
      "public_name": "Dieren",
      "is_public_accessible": false,
      "is_active": true,
      "meta": {
        "msb": {
          "code": "25",
          "onderwerpen": [
            {
              "code": "24",
              "magMelden": true,
              "omschrijving": "Dieren overig",
              "magDoorverwijzen": true,
              "indicatieBestandsbeheer": false
            },
            {
              "code": "180",
              "magMelden": true,
              "omschrijving": "Dode duiven",
              "magDoorverwijzen": true,
              "indicatieBestandsbeheer": false
            },
            {
              "code": "213",
              "magMelden": true,
              "omschrijving": "Dode ratten",
              "magDoorverwijzen": true,
              "indicatieBestandsbeheer": false
            },
            {
              "code": "125",
              "magMelden": true,
              "omschrijving": "Dode vogels",
              "magDoorverwijzen": true,
              "indicatieBestandsbeheer": false
            },
            {
              "code": "135",
              "magMelden": true,
              "omschrijving": "Dood dier in/aan water (geen rat/duif)",
              "magDoorverwijzen": true,
              "indicatieBestandsbeheer": false
            },
            {
              "code": "126",
              "magMelden": true,
              "omschrijving": "Dood dier op/aan weg (geen rat/duif)",
              "magDoorverwijzen": true,
              "indicatieBestandsbeheer": false
            },
            {
              "code": "110",
              "magMelden": true,
              "omschrijving": "Duivenoverlast",
              "magDoorverwijzen": true,
              "indicatieBestandsbeheer": false
            },
            {
              "code": "223",
              "magMelden": true,
              "omschrijving": "Eikenprocessierups",
              "magDoorverwijzen": true,
              "indicatieBestandsbeheer": false
            },
            {
              "code": "214",
              "magMelden": true,
              "omschrijving": "Levende ratten",
              "magDoorverwijzen": true,
              "indicatieBestandsbeheer": false
            },
            {
              "code": "182",
              "magMelden": true,
              "omschrijving": "Overlast wespen, bijen, hommels",
              "magDoorverwijzen": true,
              "indicatieBestandsbeheer": false
            },
            {
              "code": "197",
              "magMelden": true,
              "omschrijving": "Rat in woning of tuin (dood of levend)",
              "magDoorverwijzen": true,
              "indicatieBestandsbeheer": false
            }
          ],
          "omschrijving": "Dieren"
        }
      }
    }
  },
  {
    "model": "groups.group",
    "pk": "95112c42-16a5-4be6-a741-75494fd813e8",
    "fields": {
      "created_at": "2023-08-21T13:23:19.374Z",
      "updated_at": "2023-08-21T13:23:19.374Z",
      "name": "Wildplakken",
      "slug": "wildplakken",
      "public_name": "Wildplakken",
      "is_public_accessible": false,
      "is_active": true,
      "meta": {
        "msb": {
          "code": "36",
          "onderwerpen": [
            {
              "code": "206",
              "magMelden": true,
              "omschrijving": "Posters",
              "magDoorverwijzen": true,
              "indicatieBestandsbeheer": false
            },
            {
              "code": "170",
              "magMelden": true,
              "omschrijving": "Reclamebord",
              "magDoorverwijzen": false,
              "indicatieBestandsbeheer": false
            },
            {
              "code": "169",
              "magMelden": true,
              "omschrijving": "Sandwichborden",
              "magDoorverwijzen": false,
              "indicatieBestandsbeheer": false
            },
            {
              "code": "207",
              "magMelden": true,
              "omschrijving": "Stickers",
              "magDoorverwijzen": true,
              "indicatieBestandsbeheer": false
            }
          ],
          "omschrijving": "Wildplakken"
        }
      }
    }
  },
  {
    "model": "groups.group",
    "pk": "b2009fdb-4c4b-471d-9dd9-d654951b6f78",
    "fields": {
      "created_at": "2023-08-21T13:23:19.367Z",
      "updated_at": "2023-08-21T13:23:19.367Z",
      "name": "Straatmeubilair kapot",
      "slug": "straatmeubilair-kapot",
      "public_name": "Straatmeubilair kapot",
      "is_public_accessible": false,
      "is_active": true,
      "meta": {
        "msb": {
          "code": "19",
          "onderwerpen": [
            {
              "code": "174",
              "magMelden": true,
              "omschrijving": "bewegwijzering",
              "magDoorverwijzen": true,
              "indicatieBestandsbeheer": false
            },
            {
              "code": "134",
              "magMelden": true,
              "omschrijving": "klok / uurwerk ",
              "magDoorverwijzen": true,
              "indicatieBestandsbeheer": false
            },
            {
              "code": "171",
              "magMelden": true,
              "omschrijving": "openbaar oplaadpunt elektrische auto",
              "magDoorverwijzen": true,
              "indicatieBestandsbeheer": true
            },
            {
              "code": "69",
              "magMelden": true,
              "omschrijving": "straatmeubilair algemeen",
              "magDoorverwijzen": true,
              "indicatieBestandsbeheer": true
            },
            {
              "code": "60",
              "magMelden": true,
              "omschrijving": "straatnaambord/verkeersbord",
              "magDoorverwijzen": true,
              "indicatieBestandsbeheer": true
            },
            {
              "code": "298",
              "magMelden": true,
              "omschrijving": "Watertappunt",
              "magDoorverwijzen": true,
              "indicatieBestandsbeheer": false
            }
          ],
          "omschrijving": "Straatmeubilair kapot"
        }
      }
    }
  },
  {
    "model": "groups.group",
    "pk": "bea01995-797d-4907-9cbe-d77e88d1c714",
    "fields": {
      "created_at": "2023-08-21T13:23:19.370Z",
      "updated_at": "2023-08-21T13:23:19.370Z",
      "name": "Vuil op straat",
      "slug": "vuil-op-straat",
      "public_name": "Vuil op straat",
      "is_public_accessible": false,
      "is_active": true,
      "meta": {
        "msb": {
          "code": "27",
          "onderwerpen": [
            {
              "code": "281",
              "magMelden": true,
              "omschrijving": "Andere uitwerpselen",
              "magDoorverwijzen": true,
              "indicatieBestandsbeheer": false
            },
            {
              "code": "280",
              "magMelden": true,
              "omschrijving": "Ganzen- of eendenpoep",
              "magDoorverwijzen": true,
              "indicatieBestandsbeheer": false
            },
            {
              "code": "46",
              "magMelden": true,
              "omschrijving": "glas op straat",
              "magDoorverwijzen": true,
              "indicatieBestandsbeheer": false
            },
            {
              "code": "81",
              "magMelden": true,
              "omschrijving": "hondenpoep op straat",
              "magDoorverwijzen": true,
              "indicatieBestandsbeheer": false
            },
            {
              "code": "80",
              "magMelden": true,
              "omschrijving": "honden-uitlaatzone",
              "magDoorverwijzen": true,
              "indicatieBestandsbeheer": false
            },
            {
              "code": "299",
              "magMelden": true,
              "omschrijving": "Kerstboom op straat",
              "magDoorverwijzen": true,
              "indicatieBestandsbeheer": false
            },
            {
              "code": "282",
              "magMelden": true,
              "omschrijving": "Onkruid in groen ",
              "magDoorverwijzen": true,
              "indicatieBestandsbeheer": false
            },
            {
              "code": "44",
              "magMelden": true,
              "omschrijving": "Onkruid op verharding",
              "magDoorverwijzen": true,
              "indicatieBestandsbeheer": false
            },
            {
              "code": "301",
              "magMelden": true,
              "omschrijving": "Overlast blad of bloesem",
              "magDoorverwijzen": true,
              "indicatieBestandsbeheer": false
            },
            {
              "code": "215",
              "magMelden": true,
              "omschrijving": "zwerfvuil in het water",
              "magDoorverwijzen": true,
              "indicatieBestandsbeheer": false
            },
            {
              "code": "42",
              "magMelden": true,
              "omschrijving": "zwerfvuil in plantsoen",
              "magDoorverwijzen": true,
              "indicatieBestandsbeheer": false
            },
            {
              "code": "47",
              "magMelden": true,
              "omschrijving": "zwerfvuil op straat",
              "magDoorverwijzen": true,
              "indicatieBestandsbeheer": false
            }
          ],
          "omschrijving": "Vuil op straat"
        }
      }
    }
  },
  {
    "model": "groups.group",
    "pk": "c2d892e4-257a-4ce3-b8e5-968b1ef5766b",
    "fields": {
      "created_at": "2023-08-21T13:23:19.373Z",
      "updated_at": "2023-08-21T13:23:19.373Z",
      "name": "(Weg)werkzaamheden",
      "slug": "wegwerkzaamheden",
      "public_name": "(Weg)werkzaamheden",
      "is_public_accessible": false,
      "is_active": true,
      "meta": {
        "msb": {
          "code": "22",
          "onderwerpen": [
            {
              "code": "141",
              "magMelden": true,
              "omschrijving": "bouwplaatsen - algemeen",
              "magDoorverwijzen": true,
              "indicatieBestandsbeheer": false
            },
            {
              "code": "32",
              "magMelden": true,
              "omschrijving": "ingraving - huisaansluiting",
              "magDoorverwijzen": true,
              "indicatieBestandsbeheer": false
            },
            {
              "code": "18",
              "magMelden": true,
              "omschrijving": "tijdelijke verkeerssituatie",
              "magDoorverwijzen": true,
              "indicatieBestandsbeheer": false
            }
          ],
          "omschrijving": "(Weg)werkzaamheden"
        }
      }
    }
  },
  {
    "model": "groups.group",
    "pk": "c76a4c7f-48d0-4040-b9c5-f715d0114369",
    "fields": {
      "created_at": "2023-08-21T13:23:19.374Z",
      "updated_at": "2023-08-21T13:23:19.374Z",
      "name": "Winkelwagens",
      "slug": "winkelwagens",
      "public_name": "Winkelwagens",
      "is_public_accessible": false,
      "is_active": true,
      "meta": {
        "msb": {
          "code": "33",
          "onderwerpen": [
            {
              "code": "56",
              "magMelden": true,
              "omschrijving": "winkelwagens",
              "magDoorverwijzen": true,
              "indicatieBestandsbeheer": false
            }
          ],
          "omschrijving": "Winkelwagens"
        }
      }
    }
  },
  {
    "model": "groups.group",
    "pk": "cbc97f98-b0e7-44c3-a577-3317826ffc3f",
    "fields": {
      "created_at": "2023-08-21T13:23:19.358Z",
      "updated_at": "2023-08-21T13:23:19.358Z",
      "name": "Afvalcontainer+Prullenbak",
      "slug": "afvalcontainerprullenbak",
      "public_name": "Afvalcontainer+Prullenbak",
      "is_public_accessible": false,
      "is_active": true,
      "meta": {
        "msb": {
          "code": "23",
          "onderwerpen": [
            {
              "code": "275",
              "magMelden": true,
              "omschrijving": "Bouw/puincontainer",
              "magDoorverwijzen": true,
              "indicatieBestandsbeheer": false
            },
            {
              "code": "83",
              "magMelden": true,
              "omschrijving": "cocon/1100 liter rolcontainer vol",
              "magDoorverwijzen": true,
              "indicatieBestandsbeheer": false
            },
            {
              "code": "212",
              "magMelden": true,
              "omschrijving": "Containerruimte markthal",
              "magDoorverwijzen": true,
              "indicatieBestandsbeheer": false
            },
            {
              "code": "146",
              "magMelden": true,
              "omschrijving": "glascontainer kapot",
              "magDoorverwijzen": true,
              "indicatieBestandsbeheer": false
            },
            {
              "code": "82",
              "magMelden": true,
              "omschrijving": "glascontainer vol",
              "magDoorverwijzen": true,
              "indicatieBestandsbeheer": false
            },
            {
              "code": "279",
              "magMelden": true,
              "omschrijving": "Huiscontainer (gfe+t/gft) niet geleegd",
              "magDoorverwijzen": true,
              "indicatieBestandsbeheer": false
            },
            {
              "code": "303",
              "magMelden": true,
              "omschrijving": "Huiscontainer kapot",
              "magDoorverwijzen": true,
              "indicatieBestandsbeheer": false
            },
            {
              "code": "278",
              "magMelden": true,
              "omschrijving": "Huiscontainer (papier) niet geleegd",
              "magDoorverwijzen": true,
              "indicatieBestandsbeheer": false
            },
            {
              "code": "277",
              "magMelden": true,
              "omschrijving": "Huiscontainer (rest) niet geleegd",
              "magDoorverwijzen": true,
              "indicatieBestandsbeheer": false
            },
            {
              "code": "148",
              "magMelden": true,
              "omschrijving": "papiercontainer kapot",
              "magDoorverwijzen": true,
              "indicatieBestandsbeheer": false
            },
            {
              "code": "4",
              "magMelden": true,
              "omschrijving": "papiercontainer vol",
              "magDoorverwijzen": true,
              "indicatieBestandsbeheer": false
            },
            {
              "code": "149",
              "magMelden": true,
              "omschrijving": "prullenbak kapot",
              "magDoorverwijzen": true,
              "indicatieBestandsbeheer": false
            },
            {
              "code": "45",
              "magMelden": true,
              "omschrijving": "prullenbak vol ",
              "magDoorverwijzen": true,
              "indicatieBestandsbeheer": false
            },
            {
              "code": "109",
              "magMelden": true,
              "omschrijving": "restafvalcontainer kapot",
              "magDoorverwijzen": true,
              "indicatieBestandsbeheer": false
            },
            {
              "code": "84",
              "magMelden": true,
              "omschrijving": "restafvalcontainer vol",
              "magDoorverwijzen": true,
              "indicatieBestandsbeheer": false
            },
            {
              "code": "150",
              "magMelden": true,
              "omschrijving": "textielcontainer kapot",
              "magDoorverwijzen": true,
              "indicatieBestandsbeheer": false
            },
            {
              "code": "102",
              "magMelden": true,
              "omschrijving": "textielcontainer vol",
              "magDoorverwijzen": true,
              "indicatieBestandsbeheer": false
            },
            {
              "code": "293",
              "magMelden": true,
              "omschrijving": "Wijkcontainer (gfe) kapot",
              "magDoorverwijzen": true,
              "indicatieBestandsbeheer": false
            },
            {
              "code": "292",
              "magMelden": true,
              "omschrijving": "Wijkcontainer (gfe) vol",
              "magDoorverwijzen": true,
              "indicatieBestandsbeheer": false
            }
          ],
          "omschrijving": "Afvalcontainer+Prullenbak"
        }
      }
    }
  },
  {
    "model": "groups.group",
    "pk": "e1ed2b53-add6-4bb3-a41d-7e36f2fa96e4",
    "fields": {
      "created_at": "2023-08-21T13:23:19.356Z",
      "updated_at": "2023-08-21T13:23:19.356Z",
      "name": "Afval",
      "slug": "afval",
      "public_name": "Afval",
      "is_public_accessible": false,
      "is_active": true,
      "meta": {
        "msb": {
          "code": "1",
          "onderwerpen": [
            {
              "code": "86",
              "magMelden": true,
              "omschrijving": "bedrijfsafval",
              "magDoorverwijzen": true,
              "indicatieBestandsbeheer": false
            },
            {
              "code": "1",
              "magMelden": true,
              "omschrijving": "Grofvuil in plantsoen",
              "magDoorverwijzen": true,
              "indicatieBestandsbeheer": false
            },
            {
              "code": "276",
              "magMelden": true,
              "omschrijving": "Grofvuil op straat",
              "magDoorverwijzen": true,
              "indicatieBestandsbeheer": false
            },
            {
              "code": "93",
              "magMelden": true,
              "omschrijving": "grond/zand/grind",
              "magDoorverwijzen": true,
              "indicatieBestandsbeheer": false
            },
            {
              "code": "5",
              "magMelden": true,
              "omschrijving": "huisvuil verkeerd aangeboden",
              "magDoorverwijzen": true,
              "indicatieBestandsbeheer": false
            },
            {
              "code": "116",
              "magMelden": true,
              "omschrijving": "huisvuilzakken naast container",
              "magDoorverwijzen": true,
              "indicatieBestandsbeheer": false
            },
            {
              "code": "112",
              "magMelden": true,
              "omschrijving": "huisvuilzakken niet opgehaald",
              "magDoorverwijzen": true,
              "indicatieBestandsbeheer": false
            },
            {
              "code": "284",
              "magMelden": true,
              "omschrijving": "Klein Afval",
              "magDoorverwijzen": true,
              "indicatieBestandsbeheer": false
            },
            {
              "code": "103",
              "magMelden": true,
              "omschrijving": "koelkast/vriezer",
              "magDoorverwijzen": true,
              "indicatieBestandsbeheer": false
            },
            {
              "code": "191",
              "magMelden": true,
              "omschrijving": "Papier/Karton",
              "magDoorverwijzen": true,
              "indicatieBestandsbeheer": false
            },
            {
              "code": "106",
              "magMelden": true,
              "omschrijving": "sloopafval",
              "magDoorverwijzen": true,
              "indicatieBestandsbeheer": false
            }
          ],
          "omschrijving": "Afval"
        }
      }
    }
  },
  {
    "model": "groups.group",
    "pk": "e2232100-0ea8-41a3-876b-77702090e5e0",
    "fields": {
      "created_at": "2023-08-21T13:23:19.366Z",
      "updated_at": "2023-08-21T13:23:19.366Z",
      "name": "Speelplaatsen",
      "slug": "speelplaatsen",
      "public_name": "Speelplaatsen",
      "is_public_accessible": false,
      "is_active": true,
      "meta": {
        "msb": {
          "code": "9",
          "onderwerpen": [
            {
              "code": "40",
              "magMelden": true,
              "omschrijving": "speelplaats",
              "magDoorverwijzen": true,
              "indicatieBestandsbeheer": false
            }
          ],
          "omschrijving": "Speelplaatsen"
        }
      }
    }
  }
  ]
